[
    {
        "start": 0.0,
        "end": 14.04,
        "text": "۞ لا يحب الله الجهر بالسوء من القول إلا من ظلم ۚ وكان الله سميعا عليما"
    },
    {
        "start": 14.04,
        "end": 29.48,
        "text": "إن تبدوا خيرا أو تخفوه أو تعفوا عن سوء فإن الله كان عفوا قديرا"
    },
    {
        "start": 29.48,
        "end": 58.66,
        "text": "إن الذين يكفرون بالله ورسله ويريدون أن يفرقوا بين الله ورسله ويقولون نؤمن ببعض ونكفر ببعض ويريدون أن يتخذوا بين ذلك سبيلا"
    },
    {
        "start": 58.66,
        "end": 71.58,
        "text": "أولئك هم الكافرون حقا ۚ وأعتدنا للكافرين عذابا مهينا"
    },
    {
        "start": 71.58,
        "end": 94.8,
        "text": "والذين آمنوا بالله ورسله ولم يفرقوا بين أحد منهم أولئك سوف يؤتيهم أجورهم ۗ وكان الله غفورا رحيما"
    },
    {
        "start": 94.8,
        "end": 142.86,
        "text": "يسألك أهل الكتاب أن تنزل عليهم كتابا من السماء ۚ فقد سألوا موسى أكبر من ذلك فقالوا أرنا الله جهرة فأخذتهم الصاعقة بظلمهم ۚ ثم اتخذوا العجل من بعد ما جاءتهم البينات فعفونا عن ذلك ۚ وآتينا موسى سلطانا مبينا"
    },
    {
        "start": 142.86,
        "end": 164.84,
        "text": "ورفعنا فوقهم الطور بميثاقهم وقلنا لهم ادخلوا الباب سجدا وقلنا لهم لا تعدوا في السبت وأخذنا منهم ميثاقا غليظا"
    },
    {
        "start": 164.84,
        "end": 193.18,
        "text": "فبما نقضهم ميثاقهم وكفرهم بآيات الله وقتلهم الأنبياء بغير حق وقولهم قلوبنا غلف ۚ بل طبع الله عليها بكفرهم فلا يؤمنون إلا قليلا"
    },
    {
        "start": 193.18,
        "end": 202.14,
        "text": "وبكفرهم وقولهم على مريم بهتانا عظيما"
    },
    {
        "start": 202.14,
        "end": 238.76,
        "text": "وقولهم إنا قتلنا المسيح عيسى ابن مريم رسول الله وما قتلوه وما صلبوه ولكن شبه لهم ۚ وإن الذين اختلفوا فيه لفي شك منه ۚ ما لهم به من علم إلا اتباع الظن ۚ وما قتلوه يقينا"
    },
    {
        "start": 238.76,
        "end": 248.92,
        "text": "بل رفعه الله إليه ۚ وكان الله عزيزا حكيما"
    },
    {
        "start": 248.92,
        "end": 264.32,
        "text": "وإن من أهل الكتاب إلا ليؤمنن به قبل موته ۖ ويوم القيامة يكون عليهم شهيدا"
    },
    {
        "start": 264.32,
        "end": 281.72,
        "text": "فبظلم من الذين هادوا حرمنا عليهم طيبات أحلت لهم وبصدهم عن سبيل الله كثيرا"
    },
    {
        "start": 281.72,
        "end": 300.52,
        "text": "وأخذهم الربا وقد نهوا عنه وأكلهم أموال الناس بالباطل ۚ وأعتدنا للكافرين منهم عذابا أليما"
    },
    {
        "start": 300.52,
        "end": 337.12,
        "text": "لكن الراسخون في العلم منهم والمؤمنون يؤمنون بما أنزل إليك وما أنزل من قبلك ۚ والمقيمين الصلاة ۚ والمؤتون الزكاة والمؤمنون بالله واليوم الآخر أولئك سنؤتيهم أجرا عظيما"
    },
    {
        "start": 337.12,
        "end": 373.04,
        "text": "۞ إنا أوحينا إليك كما أوحينا إلى نوح والنبيين من بعده ۚ وأوحينا إلى إبراهيم وإسماعيل وإسحاق ويعقوب والأسباط وعيسى وأيوب ويونس وهارون وسليمان ۚ وآتينا داوود زبورا"
    },
    {
        "start": 373.04,
        "end": 389.56,
        "text": "ورسلا قد قصصناهم عليك من قبل ورسلا لم نقصصهم عليك ۚ وكلم الله موسى تكليما"
    },
    {
        "start": 389.56,
        "end": 410.56,
        "text": "رسلا مبشرين ومنذرين لئلا يكون للناس على الله حجة بعد الرسل ۚ وكان الله عزيزا حكيما"
    },
    {
        "start": 410.56,
        "end": 431.68,
        "text": "لكن الله يشهد بما أنزل إليك ۖ أنزله بعلمه ۖ والملائكة يشهدون ۚ وكفى بالله شهيدا"
    },
    {
        "start": 431.68,
        "end": 444.52,
        "text": "إن الذين كفروا وصدوا عن سبيل الله قد ضلوا ضلالا بعيدا"
    },
    {
        "start": 444.52,
        "end": 457.46,
        "text": "إن الذين كفروا وظلموا لم يكن الله ليغفر لهم ولا ليهديهم طريقا"
    },
    {
        "start": 457.46,
        "end": 471.86,
        "text": "إلا طريق جهنم خالدين فيها أبدا ۚ وكان ذلك على الله يسيرا"
    },
    {
        "start": 471.86,
        "end": 501.14,
        "text": "يا أيها الناس قد جاءكم الرسول بالحق من ربكم فآمنوا خيرا لكم ۚ وإن تكفروا فإن لله ما في السماوات والأرض ۚ وكان الله عليما حكيما"
    },
    {
        "start": 501.14,
        "end": 565.22,
        "text": "يا أهل الكتاب لا تغلوا في دينكم ولا تقولوا على الله إلا الحق ۚ إنما المسيح عيسى ابن مريم رسول الله وكلمته ألقاها إلى مريم وروح منه ۖ فآمنوا بالله ورسله ۖ ولا تقولوا ثلاثة ۚ انتهوا خيرا لكم ۚ إنما الله إله واحد ۖ سبحانه أن يكون له ولد ۘ له ما في السماوات وما في الأرض ۗ وكفى بالله وكيلا"
    },
    {
        "start": 565.22,
        "end": 592.08,
        "text": "لن يستنكف المسيح أن يكون عبدا لله ولا الملائكة المقربون ۚ ومن يستنكف عن عبادته ويستكبر فسيحشرهم إليه جميعا"
    },
    {
        "start": 592.08,
        "end": 630.84,
        "text": "فأما الذين آمنوا وعملوا الصالحات فيوفيهم أجورهم ويزيدهم من فضله ۖ وأما الذين استنكفوا واستكبروا فيعذبهم عذابا أليما ولا يجدون لهم من دون الله وليا ولا نصيرا"
    },
    {
        "start": 630.84,
        "end": 648.74,
        "text": "يا أيها الناس قد جاءكم برهان من ربكم وأنزلنا إليكم نورا مبينا"
    },
    {
        "start": 648.74,
        "end": 670.26,
        "text": "فأما الذين آمنوا بالله واعتصموا به فسيدخلهم في رحمة منه وفضل ويهديهم إليه صراطا مستقيما"
    },
    {
        "start": 671.3,
        "end": 731.58,
        "text": "يستفتونك قل الله يفتيكم في الكلالة ۚ إن امرؤ هلك ليس له ولد وله أخت فلها نصف ما ترك ۚ وهو يرثها إن لم يكن لها ولد ۚ فإن كانتا اثنتين فلهما الثلثان مما ترك ۚ وإن كانوا إخوة رجالا ونساء فللذكر مثل حظ الأنثيين ۗ يبين الله لكم أن تضلوا ۗ والله بكل شيء عليم"
    },
    {
        "start": 731.58,
        "end": 766.44,
        "text": "بسم الله الرحمن الرحيم يا أيها الذين آمنوا أوفوا بالعقود ۚ أحلت لكم بهيمة الأنعام إلا ما يتلى عليكم غير محلي الصيد وأنتم حرم ۗ إن الله يحكم ما يريد"
    },
    {
        "start": 766.44,
        "end": 838.02,
        "text": "يا أيها الذين آمنوا لا تحلوا شعائر الله ولا الشهر الحرام ولا الهدي ولا القلائد ولا آمين البيت الحرام يبتغون فضلا من ربهم ورضوانا ۚ وإذا حللتم فاصطادوا ۚ ولا يجرمنكم شنآن قوم أن صدوكم عن المسجد الحرام أن تعتدوا ۘ وتعاونوا على البر والتقوى ۖ ولا تعاونوا على الإثم والعدوان ۚ واتقوا الله ۖ إن الله شديد العقاب"
    },
    {
        "start": 838.02,
        "end": 925.16,
        "text": "حرمت عليكم الميتة والدم ولحم الخنزير وما أهل لغير الله به والمنخنقة والموقوذة والمتردية والنطيحة وما أكل السبع إلا ما ذكيتم وما ذبح على النصب وأن تستقسموا بالأزلام ۚ ذلكم فسق ۗ اليوم يئس الذين كفروا من دينكم فلا تخشوهم واخشون ۚ اليوم أكملت لكم دينكم وأتممت عليكم نعمتي ورضيت لكم الإسلام دينا ۚ فمن اضطر في مخمصة غير متجانف لإثم ۙ فإن الله غفور رحيم"
    },
    {
        "start": 925.16,
        "end": 968.06,
        "text": "يسألونك ماذا أحل لهم ۖ قل أحل لكم الطيبات ۙ وما علمتم من الجوارح مكلبين تعلمونهن مما علمكم الله ۖ فكلوا مما أمسكن عليكم واذكروا اسم الله عليه ۖ واتقوا الله ۚ إن الله سريع الحساب"
    },
    {
        "start": 968.06,
        "end": 1034.44,
        "text": "اليوم أحل لكم الطيبات ۖ وطعام الذين أوتوا الكتاب حل لكم وطعامكم حل لهم ۖ والمحصنات من المؤمنات والمحصنات من الذين أوتوا الكتاب من قبلكم إذا آتيتموهن أجورهن محصنين غير مسافحين ولا متخذي أخدان ۗ ومن يكفر بالإيمان فقد حبط عمله وهو في الآخرة من الخاسرين"
    },
    {
        "start": 1034.44,
        "end": 1121.3,
        "text": "يا أيها الذين آمنوا إذا قمتم إلى الصلاة فاغسلوا وجوهكم وأيديكم إلى المرافق وامسحوا برءوسكم وأرجلكم إلى الكعبين ۚ وإن كنتم جنبا فاطهروا ۚ وإن كنتم مرضى أو على سفر أو جاء أحد منكم من الغائط أو لامستم النساء فلم تجدوا ماء فتيمموا صعيدا طيبا فامسحوا بوجوهكم وأيديكم منه ۚ ما يريد الله ليجعل عليكم من حرج ولكن يريد ليطهركم وليتم نعمته عليكم لعلكم تشكرون"
    },
    {
        "start": 1121.3,
        "end": 1146.74,
        "text": "واذكروا نعمة الله عليكم وميثاقه الذي واثقكم به إذ قلتم سمعنا وأطعنا ۖ واتقوا الله ۚ إن الله عليم بذات الصدور"
    },
    {
        "start": 1146.74,
        "end": 1183.7,
        "text": "يا أيها الذين آمنوا كونوا قوامين لله شهداء بالقسط ۖ ولا يجرمنكم شنآن قوم على ألا تعدلوا ۚ اعدلوا هو أقرب للتقوى ۖ واتقوا الله ۚ إن الله خبير بما تعملون"
    },
    {
        "start": 1184.26,
        "end": 1196.22,
        "text": "وعد الله الذين آمنوا وعملوا الصالحات ۙ لهم مغفرة وأجر عظيم"
    },
    {
        "start": 1196.22,
        "end": 1207.06,
        "text": "والذين كفروا وكذبوا بآياتنا أولئك أصحاب الجحيم"
    },
    {
        "start": 1207.06,
        "end": 1236.26,
        "text": "يا أيها الذين آمنوا اذكروا نعمت الله عليكم إذ هم قوم أن يبسطوا إليكم أيديهم فكف أيديهم عنكم ۖ واتقوا الله ۚ وعلى الله فليتوكل المؤمنون"
    },
    {
        "start": 1236.26,
        "end": 1312.2,
        "text": "۞ ولقد أخذ الله ميثاق بني إسرائيل وبعثنا منهم اثني عشر نقيبا ۖ وقال الله إني معكم ۖ لئن أقمتم الصلاة وآتيتم الزكاة وآمنتم برسلي وعزرتموهم وأقرضتم الله قرضا حسنا لأكفرن عنكم سيئاتكم ولأدخلنكم جنات تجري من تحتها الأنهار ۚ فمن كفر بعد ذلك منكم فقد ضل سواء السبيل"
    },
    {
        "start": 1312.2,
        "end": 1356.22,
        "text": "فبما نقضهم ميثاقهم لعناهم وجعلنا قلوبهم قاسية ۖ يحرفون الكلم عن مواضعه ۙ ونسوا حظا مما ذكروا به ۚ ولا تزال تطلع على خائنة منهم إلا قليلا منهم ۖ فاعف عنهم واصفح ۚ إن الله يحب المحسنين"
    },
    {
        "start": 1356.22,
        "end": 1390.42,
        "text": "ومن الذين قالوا إنا نصارى أخذنا ميثاقهم فنسوا حظا مما ذكروا به فأغرينا بينهم العداوة والبغضاء إلى يوم القيامة ۚ وسوف ينبئهم الله بما كانوا يصنعون"
    },
    {
        "start": 1390.42,
        "end": 1422.1,
        "text": "يا أهل الكتاب قد جاءكم رسولنا يبين لكم كثيرا مما كنتم تخفون من الكتاب ويعفو عن كثير ۚ قد جاءكم من الله نور وكتاب مبين"
    },
    {
        "start": 1422.1,
        "end": 1445.64,
        "text": "يهدي به الله من اتبع رضوانه سبل السلام ويخرجهم من الظلمات إلى النور بإذنه ويهديهم إلى صراط مستقيم"
    },
    {
        "start": 1445.64,
        "end": 1497.32,
        "text": "لقد كفر الذين قالوا إن الله هو المسيح ابن مريم ۚ قل فمن يملك من الله شيئا إن أراد أن يهلك المسيح ابن مريم وأمه ومن في الأرض جميعا ۗ ولله ملك السماوات والأرض وما بينهما ۚ يخلق ما يشاء ۚ والله على كل شيء قدير"
    },
    {
        "start": 1497.32,
        "end": 1544.46,
        "text": "وقالت اليهود والنصارى نحن أبناء الله وأحباؤه ۚ قل فلم يعذبكم بذنوبكم ۖ بل أنتم بشر ممن خلق ۚ يغفر لمن يشاء ويعذب من يشاء ۚ ولله ملك السماوات والأرض وما بينهما ۖ وإليه المصير"
    },
    {
        "start": 1544.46,
        "end": 1582.36,
        "text": "يا أهل الكتاب قد جاءكم رسولنا يبين لكم على فترة من الرسل أن تقولوا ما جاءنا من بشير ولا نذير ۖ فقد جاءكم بشير ونذير ۗ والله على كل شيء قدير"
    },
    {
        "start": 1582.36,
        "end": 1610.94,
        "text": "وإذ قال موسى لقومه يا قوم اذكروا نعمة الله عليكم إذ جعل فيكم أنبياء وجعلكم ملوكا وآتاكم ما لم يؤت أحدا من العالمين"
    },
    {
        "start": 1610.94,
        "end": 1629.94,
        "text": "يا قوم ادخلوا الأرض المقدسة التي كتب الله لكم ولا ترتدوا على أدباركم فتنقلبوا خاسرين"
    },
    {
        "start": 1629.94,
        "end": 1655.3,
        "text": "قالوا يا موسى إن فيها قوما جبارين وإنا لن ندخلها حتى يخرجوا منها فإن يخرجوا منها فإنا داخلون"
    },
    {
        "start": 1655.3,
        "end": 1687.12,
        "text": "قال رجلان من الذين يخافون أنعم الله عليهما ادخلوا عليهم الباب فإذا دخلتموه فإنكم غالبون ۚ وعلى الله فتوكلوا إن كنتم مؤمنين"
    },
    {
        "start": 1687.12,
        "end": 1710.2,
        "text": "قالوا يا موسى إنا لن ندخلها أبدا ما داموا فيها ۖ فاذهب أنت وربك فقاتلا إنا هاهنا قاعدون"
    },
    {
        "start": 1710.2,
        "end": 1726.74,
        "text": "قال رب إني لا أملك إلا نفسي وأخي ۖ فافرق بيننا وبين القوم الفاسقين"
    },
    {
        "start": 1734.0,
        "end": 1746.5,
        "text": "قال فإنها محرمة عليهم ۛ أربعين سنة ۛ يتيهون في الأرض ۚ فلا تأس على القوم الفاسقين"
    },
    {
        "start": 1746.5,
        "end": 1774.78,
        "text": "۞ واتل عليهم نبأ ابني آدم بالحق إذ قربا قربانا فتقبل من أحدهما ولم يتقبل من الآخر قال لأقتلنك ۖ قال إنما يتقبل الله من المتقين"
    },
    {
        "start": 1774.78,
        "end": 1792.8,
        "text": "لئن بسطت إلي يدك لتقتلني ما أنا بباسط يدي إليك لأقتلك ۖ إني أخاف الله رب العالمين"
    },
    {
        "start": 1792.8,
        "end": 1812.44,
        "text": "إني أريد أن تبوء بإثمي وإثمك فتكون من أصحاب النار ۚ وذلك جزاء الظالمين"
    },
    {
        "start": 1812.44,
        "end": 1823.72,
        "text": "فطوعت له نفسه قتل أخيه فقتله فأصبح من الخاسرين"
    },
    {
        "start": 1823.72,
        "end": 1851.86,
        "text": "فبعث الله غرابا يبحث في الأرض ليريه كيف يواري سوءة أخيه ۚ قال يا ويلتا أعجزت أن أكون مثل هذا الغراب فأواري سوءة أخي ۖ فأصبح من النادمين"
    },
    {
        "start": 1851.86,
        "end": 1905.92,
        "text": "من أجل ذلك كتبنا على بني إسرائيل أنه من قتل نفسا بغير نفس أو فساد في الأرض فكأنما قتل الناس جميعا ومن أحياها فكأنما أحيا الناس جميعا ۚ ولقد جاءتهم رسلنا بالبينات ثم إن كثيرا منهم بعد ذلك في الأرض لمسرفون"
    },
    {
        "start": 1908.22,
        "end": 1947.02,
        "text": "إنما جزاء الذين يحاربون الله ورسوله ويسعون في الأرض فسادا أن يقتلوا أو يصلبوا أو تقطع أيديهم وأرجلهم من خلاف أو ينفوا من الأرض ۚ ذلك لهم خزي في الدنيا ۖ ولهم في الآخرة عذاب عظيم"
    },
    {
        "start": 1947.9,
        "end": 1962.54,
        "text": "إلا الذين تابوا من قبل أن تقدروا عليهم ۖ فاعلموا أن الله غفور رحيم"
    },
    {
        "start": 1962.54,
        "end": 1978.68,
        "text": "يا أيها الذين آمنوا اتقوا الله وابتغوا إليه الوسيلة وجاهدوا في سبيله لعلكم تفلحون"
    },
    {
        "start": 1978.68,
        "end": 2004.08,
        "text": "إن الذين كفروا لو أن لهم ما في الأرض جميعا ومثله معه ليفتدوا به من عذاب يوم القيامة ما تقبل منهم ۖ ولهم عذاب أليم"
    },
    {
        "start": 2004.08,
        "end": 2018.8,
        "text": "يريدون أن يخرجوا من النار وما هم بخارجين منها ۖ ولهم عذاب مقيم"
    },
    {
        "start": 2018.8,
        "end": 2037.88,
        "text": "والسارق والسارقة فاقطعوا أيديهما جزاء بما كسبا نكالا من الله ۗ والله عزيز حكيم"
    },
    {
        "start": 2037.88,
        "end": 2055.58,
        "text": "فمن تاب من بعد ظلمه وأصلح فإن الله يتوب عليه ۗ إن الله غفور رحيم"
    },
    {
        "start": 2055.58,
        "end": 2080.72,
        "text": "ألم تعلم أن الله له ملك السماوات والأرض يعذب من يشاء ويغفر لمن يشاء ۗ والله على كل شيء قدير"
    },
    {
        "start": 2080.72,
        "end": 2154.8,
        "text": "۞ يا أيها الرسول لا يحزنك الذين يسارعون في الكفر من الذين قالوا آمنا بأفواههم ولم تؤمن قلوبهم ۛ ومن الذين هادوا ۛ سماعون للكذب سماعون لقوم آخرين لم يأتوك ۖ يحرفون الكلم من بعد مواضعه ۖ يقولون إن أوتيتم هذا فخذوه وإن لم تؤتوه فاحذروا ۚ ومن يرد الله فتنته فلن تملك له من الله شيئا ۚ أولئك الذين لم يرد الله أن يطهر قلوبهم ۚ لهم في الدنيا خزي ۖ ولهم في الآخرة عذاب عظيم"
    },
    {
        "start": 2154.8,
        "end": 2191.36,
        "text": "سماعون للكذب أكالون للسحت ۚ فإن جاءوك فاحكم بينهم أو أعرض عنهم ۖ وإن تعرض عنهم فلن يضروك شيئا ۖ وإن حكمت فاحكم بينهم بالقسط ۚ إن الله يحب المقسطين"
    },
    {
        "start": 2192.16,
        "end": 2211.8,
        "text": "وكيف يحكمونك وعندهم التوراة فيها حكم الله ثم يتولون من بعد ذلك ۚ وما أولئك بالمؤمنين"
    },
    {
        "start": 2211.8,
        "end": 2263.5,
        "text": "إنا أنزلنا التوراة فيها هدى ونور ۚ يحكم بها النبيون الذين أسلموا للذين هادوا والربانيون والأحبار بما استحفظوا من كتاب الله وكانوا عليه شهداء ۚ فلا تخشوا الناس واخشون ولا تشتروا بآياتي ثمنا قليلا ۚ ومن لم يحكم بما أنزل الله فأولئك هم الكافرون"
    },
    {
        "start": 2263.5,
        "end": 2304.44,
        "text": "وكتبنا عليهم فيها أن النفس بالنفس والعين بالعين والأنف بالأنف والأذن بالأذن والسن بالسن والجروح قصاص ۚ فمن تصدق به فهو كفارة له ۚ ومن لم يحكم بما أنزل الله فأولئك هم الظالمون"
    },
    {
        "start": 2304.44,
        "end": 2342.64,
        "text": "وقفينا على آثارهم بعيسى ابن مريم مصدقا لما بين يديه من التوراة ۖ وآتيناه الإنجيل فيه هدى ونور ومصدقا لما بين يديه من التوراة وهدى وموعظة للمتقين"
    },
    {
        "start": 2342.64,
        "end": 2362.26,
        "text": "وليحكم أهل الإنجيل بما أنزل الله فيه ۚ ومن لم يحكم بما أنزل الله فأولئك هم الفاسقون"
    },
    {
        "start": 2363.68,
        "end": 2433.66,
        "text": "وأنزلنا إليك الكتاب بالحق مصدقا لما بين يديه من الكتاب ومهيمنا عليه ۖ فاحكم بينهم بما أنزل الله ۖ ولا تتبع أهواءهم عما جاءك من الحق ۚ لكل جعلنا منكم شرعة ومنهاجا ۚ ولو شاء الله لجعلكم أمة واحدة ولكن ليبلوكم في ما آتاكم ۖ فاستبقوا الخيرات ۚ إلى الله مرجعكم جميعا فينبئكم بما كنتم فيه تختلفون"
    },
    {
        "start": 2433.66,
        "end": 2476.3,
        "text": "وأن احكم بينهم بما أنزل الله ولا تتبع أهواءهم واحذرهم أن يفتنوك عن بعض ما أنزل الله إليك ۖ فإن تولوا فاعلم أنما يريد الله أن يصيبهم ببعض ذنوبهم ۗ وإن كثيرا من الناس لفاسقون"
    },
    {
        "start": 2476.3,
        "end": 2489.92,
        "text": "أفحكم الجاهلية يبغون ۚ ومن أحسن من الله حكما لقوم يوقنون"
    },
    {
        "start": 2489.92,
        "end": 2522.62,
        "text": "۞ يا أيها الذين آمنوا لا تتخذوا اليهود والنصارى أولياء ۘ بعضهم أولياء بعض ۚ ومن يتولهم منكم فإنه منهم ۗ إن الله لا يهدي القوم الظالمين"
    },
    {
        "start": 2522.62,
        "end": 2556.4,
        "text": "فترى الذين في قلوبهم مرض يسارعون فيهم يقولون نخشى أن تصيبنا دائرة ۚ فعسى الله أن يأتي بالفتح أو أمر من عنده فيصبحوا على ما أسروا في أنفسهم نادمين"
    },
    {
        "start": 2556.4,
        "end": 2577.28,
        "text": "ويقول الذين آمنوا أهؤلاء الذين أقسموا بالله جهد أيمانهم ۙ إنهم لمعكم ۚ حبطت أعمالهم فأصبحوا خاسرين"
    },
    {
        "start": 2577.28,
        "end": 2628.86,
        "text": "يا أيها الذين آمنوا من يرتد منكم عن دينه فسوف يأتي الله بقوم يحبهم ويحبونه أذلة على المؤمنين أعزة على الكافرين يجاهدون في سبيل الله ولا يخافون لومة لائم ۚ ذلك فضل الله يؤتيه من يشاء ۚ والله واسع عليم"
    },
    {
        "start": 2628.86,
        "end": 2644.66,
        "text": "إنما وليكم الله ورسوله والذين آمنوا الذين يقيمون الصلاة ويؤتون الزكاة وهم راكعون"
    },
    {
        "start": 2644.66,
        "end": 2658.44,
        "text": "ومن يتول الله ورسوله والذين آمنوا فإن حزب الله هم الغالبون"
    },
    {
        "start": 2658.44,
        "end": 2686.84,
        "text": "يا أيها الذين آمنوا لا تتخذوا الذين اتخذوا دينكم هزوا ولعبا من الذين أوتوا الكتاب من قبلكم والكفار أولياء ۚ واتقوا الله إن كنتم مؤمنين"
    },
    {
        "start": 2686.84,
        "end": 2702.72,
        "text": "وإذا ناديتم إلى الصلاة اتخذوها هزوا ولعبا ۚ ذلك بأنهم قوم لا يعقلون"
    },
    {
        "start": 2702.72,
        "end": 2725.86,
        "text": "قل يا أهل الكتاب هل تنقمون منا إلا أن آمنا بالله وما أنزل إلينا وما أنزل من قبل وأن أكثركم فاسقون"
    },
    {
        "start": 2725.86,
        "end": 2760.76,
        "text": "قل هل أنبئكم بشر من ذلك مثوبة عند الله ۚ من لعنه الله وغضب عليه وجعل منهم القردة والخنازير وعبد الطاغوت ۚ أولئك شر مكانا وأضل عن سواء السبيل"
    },
    {
        "start": 2760.76,
        "end": 2780.36,
        "text": "وإذا جاءوكم قالوا آمنا وقد دخلوا بالكفر وهم قد خرجوا به ۚ والله أعلم بما كانوا يكتمون"
    },
    {
        "start": 2780.36,
        "end": 2796.16,
        "text": "وترى كثيرا منهم يسارعون في الإثم والعدوان وأكلهم السحت ۚ لبئس ما كانوا يعملون"
    },
    {
        "start": 2796.16,
        "end": 2813.74,
        "text": "لولا ينهاهم الربانيون والأحبار عن قولهم الإثم وأكلهم السحت ۚ لبئس ما كانوا يصنعون"
    },
    {
        "start": 2813.74,
        "end": 2874.96,
        "text": "وقالت اليهود يد الله مغلولة ۚ غلت أيديهم ولعنوا بما قالوا ۘ بل يداه مبسوطتان ينفق كيف يشاء ۚ وليزيدن كثيرا منهم ما أنزل إليك من ربك طغيانا وكفرا ۚ وألقينا بينهم العداوة والبغضاء إلى يوم القيامة ۚ كلما أوقدوا نارا للحرب أطفأها الله ۚ ويسعون في الأرض فسادا ۚ والله لا يحب المفسدين"
    },
    {
        "start": 2874.96,
        "end": 2891.68,
        "text": "ولو أن أهل الكتاب آمنوا واتقوا لكفرنا عنهم سيئاتهم ولأدخلناهم جنات النعيم"
    },
    {
        "start": 2891.68,
        "end": 2924.1,
        "text": "ولو أنهم أقاموا التوراة والإنجيل وما أنزل إليهم من ربهم لأكلوا من فوقهم ومن تحت أرجلهم ۚ منهم أمة مقتصدة ۖ وكثير منهم ساء ما يعملون"
    },
    {
        "start": 2924.1,
        "end": 2950.06,
        "text": "۞ يا أيها الرسول بلغ ما أنزل إليك من ربك ۖ وإن لم تفعل فما بلغت رسالته ۚ والله يعصمك من الناس ۗ إن الله لا يهدي القوم الكافرين"
    },
    {
        "start": 2950.06,
        "end": 2986.04,
        "text": "قل يا أهل الكتاب لستم على شيء حتى تقيموا التوراة والإنجيل وما أنزل إليكم من ربكم ۗ وليزيدن كثيرا منهم ما أنزل إليك من ربك طغيانا وكفرا ۖ فلا تأس على القوم الكافرين"
    },
    {
        "start": 2986.04,
        "end": 3009.06,
        "text": "إن الذين آمنوا والذين هادوا والصابئون والنصارى من آمن بالله واليوم الآخر وعمل صالحا فلا خوف عليهم ولا هم يحزنون"
    },
    {
        "start": 3009.06,
        "end": 3034.12,
        "text": "لقد أخذنا ميثاق بني إسرائيل وأرسلنا إليهم رسلا ۖ كلما جاءهم رسول بما لا تهوى أنفسهم فريقا كذبوا وفريقا يقتلون"
    },
    {
        "start": 3034.12,
        "end": 3059.4,
        "text": "وحسبوا ألا تكون فتنة فعموا وصموا ثم تاب الله عليهم ثم عموا وصموا كثير منهم ۚ والله بصير بما يعملون"
    },
    {
        "start": 3059.4,
        "end": 3097.54,
        "text": "لقد كفر الذين قالوا إن الله هو المسيح ابن مريم ۖ وقال المسيح يا بني إسرائيل اعبدوا الله ربي وربكم ۖ إنه من يشرك بالله فقد حرم الله عليه الجنة ومأواه النار ۖ وما للظالمين من أنصار"
    },
    {
        "start": 3097.54,
        "end": 3125.06,
        "text": "لقد كفر الذين قالوا إن الله ثالث ثلاثة ۘ وما من إله إلا إله واحد ۚ وإن لم ينتهوا عما يقولون ليمسن الذين كفروا منهم عذاب أليم"
    },
    {
        "start": 3125.06,
        "end": 3135.86,
        "text": "أفلا يتوبون إلى الله ويستغفرونه ۚ والله غفور رحيم"
    },
    {
        "start": 3135.86,
        "end": 3166.96,
        "text": "ما المسيح ابن مريم إلا رسول قد خلت من قبله الرسل وأمه صديقة ۖ كانا يأكلان الطعام ۗ انظر كيف نبين لهم الآيات ثم انظر أنى يؤفكون"
    },
    {
        "start": 3166.96,
        "end": 3183.38,
        "text": "قل أتعبدون من دون الله ما لا يملك لكم ضرا ولا نفعا ۚ والله هو السميع العليم"
    },
    {
        "start": 3183.38,
        "end": 3208.42,
        "text": "قل يا أهل الكتاب لا تغلوا في دينكم غير الحق ولا تتبعوا أهواء قوم قد ضلوا من قبل وأضلوا كثيرا وضلوا عن سواء السبيل"
    },
    {
        "start": 3208.42,
        "end": 3228.66,
        "text": "لعن الذين كفروا من بني إسرائيل على لسان داوود وعيسى ابن مريم ۚ ذلك بما عصوا وكانوا يعتدون"
    },
    {
        "start": 3228.66,
        "end": 3241.94,
        "text": "كانوا لا يتناهون عن منكر فعلوه ۚ لبئس ما كانوا يفعلون"
    },
    {
        "start": 3241.94,
        "end": 3263.72,
        "text": "ترى كثيرا منهم يتولون الذين كفروا ۚ لبئس ما قدمت لهم أنفسهم أن سخط الله عليهم وفي العذاب هم خالدون"
    },
    {
        "start": 3263.72,
        "end": 3285.38,
        "text": "ولو كانوا يؤمنون بالله والنبي وما أنزل إليه ما اتخذوهم أولياء ولكن كثيرا منهم فاسقون"
    }
]